{
  "annotations": {
    "list": [
      {
        "builtIn": 1,
        "datasource": {
          "type": "grafana",
          "uid": "-- Grafana --"
        },
        "enable": true,
        "hide": true,
        "iconColor": "rgba(0, 211, 255, 1)",
        "name": "Annotations & Alerts",
        "type": "dashboard"
      }
    ]
  },
  "editable": true,
  "fiscalYearStartMonth": 0,
  "graphTooltip": 0,
  "id": 28,
  "links": [],
  "liveNow": false,
  "panels": [
    {
      "collapsed": false,
      "gridPos": {
        "h": 1,
        "w": 24,
        "x": 0,
        "y": 0
      },
      "id": 9,
      "panels": [],
      "title": "API Resource Metrics",
      "type": "row"
    },
    {
      "datasource": {
        "type": "prometheus",
        "uid": "prometheus"
      },
      "fieldConfig": {
        "defaults": {
          "color": {
            "mode": "palette-classic"
          },
          "custom": {
            "axisCenteredZero": false,
            "axisColorMode": "text",
            "axisLabel": "",
            "axisPlacement": "auto",
            "barAlignment": 0,
            "drawStyle": "line",
            "fillOpacity": 10,
            "gradientMode": "none",
            "hideFrom": {
              "legend": false,
              "tooltip": false,
              "viz": false
            },
            "insertNulls": false,
            "lineInterpolation": "linear",
            "lineWidth": 2,
            "pointSize": 5,
            "scaleDistribution": {
              "type": "linear"
            },
            "showPoints": "never",
            "spanNulls": true,
            "stacking": {
              "group": "A",
              "mode": "none"
            },
            "thresholdsStyle": {
              "mode": "off"
            }
          },
          "mappings": [],
          "thresholds": {
            "mode": "absolute",
            "steps": [
              {
                "color": "green",
                "value": null
              },
              {
                "color": "red",
                "value": 80
              }
            ]
          },
          "unit": "reqps"
        },
        "overrides": [
          {
            "matcher": {
              "id": "byValue",
              "options": {
                "op": "gte",
                "reducer": "allIsZero",
                "value": 0
              }
            },
            "properties": [
              {
                "id": "custom.hideFrom",
                "value": {
                  "legend": true,
                  "tooltip": true,
                  "viz": false
                }
              }
            ]
          }
        ]
      },
      "gridPos": {
        "h": 7,
        "w": 12,
        "x": 0,
        "y": 1
      },
      "id": 19,
      "links": [],
      "options": {
        "legend": {
          "calcs": [
            "mean"
          ],
          "displayMode": "table",
          "placement": "right",
          "showLegend": true,
          "width": 300
        },
        "tooltip": {
          "mode": "multi",
          "sort": "desc"
        }
      },
      "pluginVersion": "10.1.5",
      "repeatDirection": "h",
      "targets": [
        {
          "datasource": {
            "type": "prometheus",
            "uid": "prometheus"
          },
          "editorMode": "code",
          "expr": "round(sum(irate(http_server_requests_seconds_count[2m])) by (uri), 0.001)",
          "format": "time_series",
          "hide": false,
          "instant": false,
          "interval": "",
          "intervalFactor": 1,
          "legendFormat": "{{ ingress }}",
          "metric": "network",
          "refId": "A",
          "step": 10
        }
      ],
      "title": "API RPS",
      "type": "timeseries"
    },
    {
      "datasource": {
        "type": "prometheus",
        "uid": "prometheus"
      },
      "fieldConfig": {
        "defaults": {
          "color": {
            "fixedColor": "red",
            "mode": "fixed"
          },
          "mappings": [
            {
              "options": {
                "match": "null+nan",
                "result": {
                  "index": 0,
                  "text": "0%"
                }
              },
              "type": "special"
            }
          ],
          "thresholds": {
            "mode": "percentage",
            "steps": [
              {
                "color": "rgba(245, 54, 54, 0.9)",
                "value": null
              }
            ]
          },
          "unit": "percentunit"
        },
        "overrides": []
      },
      "gridPos": {
        "h": 5,
        "w": 5,
        "x": 12,
        "y": 1
      },
      "id": 20,
      "links": [],
      "maxDataPoints": 100,
      "options": {
        "colorMode": "none",
        "graphMode": "area",
        "justifyMode": "auto",
        "orientation": "horizontal",
        "reduceOptions": {
          "calcs": [],
          "fields": "",
          "values": false
        },
        "textMode": "auto"
      },
      "pluginVersion": "10.1.5",
      "targets": [
        {
          "datasource": {
            "type": "prometheus",
            "uid": "prometheus"
          },
          "editorMode": "code",
          "exemplar": false,
          "expr": "sum(increase(http_server_requests_seconds_count{status=~\"4..|5..\"}[1m])) /sum(increase(http_server_requests_seconds_count[1m]))",
          "format": "table",
          "instant": false,
          "intervalFactor": 1,
          "legendFormat": "__auto",
          "range": true,
          "refId": "A",
          "step": 4
        }
      ],
      "title": "API Error Rate  (4|5xx responses)",
      "type": "stat"
    },
    {
      "datasource": {
        "type": "prometheus",
        "uid": "prometheus"
      },
      "fieldConfig": {
        "defaults": {
          "color": {
            "fixedColor": "green",
            "mode": "fixed"
          },
          "mappings": [
            {
              "options": {
                "match": "null+nan",
                "result": {
                  "index": 0,
                  "text": "0%"
                }
              },
              "type": "special"
            }
          ],
          "thresholds": {
            "mode": "percentage",
            "steps": [
              {
                "color": "rgba(245, 54, 54, 0.9)",
                "value": null
              }
            ]
          },
          "unit": "percentunit"
        },
        "overrides": []
      },
      "gridPos": {
        "h": 5,
        "w": 5,
        "x": 17,
        "y": 1
      },
      "id": 22,
      "links": [],
      "maxDataPoints": 100,
      "options": {
        "colorMode": "none",
        "graphMode": "area",
        "justifyMode": "auto",
        "orientation": "horizontal",
        "reduceOptions": {
          "calcs": [],
          "fields": "",
          "values": false
        },
        "textMode": "auto"
      },
      "pluginVersion": "10.1.5",
      "targets": [
        {
          "datasource": {
            "type": "prometheus",
            "uid": "prometheus"
          },
          "editorMode": "code",
          "exemplar": false,
          "expr": "sum(increase(http_server_requests_seconds_count{status!~\"4..|5..\"}[1m])) /sum(increase(http_server_requests_seconds_count[1m]))",
          "format": "table",
          "instant": false,
          "intervalFactor": 1,
          "legendFormat": "__auto",
          "range": true,
          "refId": "A",
          "step": 4
        }
      ],
      "title": "API Success Rate  (non 4|5xx responses)",
      "type": "stat"
    },
    {
      "datasource": {
        "type": "prometheus",
        "uid": "prometheus"
      },
      "fieldConfig": {
        "defaults": {
          "color": {
            "mode": "palette-classic"
          },
          "custom": {
            "axisCenteredZero": false,
            "axisColorMode": "text",
            "axisLabel": "",
            "axisPlacement": "auto",
            "barAlignment": 0,
            "drawStyle": "line",
            "fillOpacity": 0,
            "gradientMode": "none",
            "hideFrom": {
              "legend": false,
              "tooltip": false,
              "viz": false
            },
            "insertNulls": false,
            "lineInterpolation": "smooth",
            "lineWidth": 1,
            "pointSize": 5,
            "scaleDistribution": {
              "type": "linear"
            },
            "showPoints": "auto",
            "spanNulls": false,
            "stacking": {
              "group": "A",
              "mode": "none"
            },
            "thresholdsStyle": {
              "mode": "off"
            }
          },
          "decimals": 0,
          "mappings": [],
          "thresholds": {
            "mode": "absolute",
            "steps": [
              {
                "color": "green",
                "value": null
              },
              {
                "color": "red",
                "value": 80
              }
            ]
          },
          "unit": "s"
        },
        "overrides": []
      },
      "gridPos": {
        "h": 6,
        "w": 12,
        "x": 0,
        "y": 8
      },
      "id": 5,
      "options": {
        "legend": {
          "calcs": [
            "min",
            "max"
          ],
          "displayMode": "table",
          "placement": "right",
          "showLegend": true
        },
        "tooltip": {
          "mode": "single",
          "sort": "none"
        }
      },
      "targets": [
        {
          "datasource": {
            "type": "prometheus",
            "uid": "prometheus"
          },
          "editorMode": "code",
          "exemplar": false,
          "expr": "histogram_quantile(0.50, \n    sum(rate(http_server_requests_seconds_bucket{uri=~\"/user.*\"}[1m])) by (le, uri)\n)",
          "format": "time_series",
          "instant": false,
          "legendFormat": "P50 {{uri}}",
          "range": true,
          "refId": "A"
        },
        {
          "datasource": {
            "type": "prometheus",
            "uid": "prometheus"
          },
          "editorMode": "code",
          "expr": "histogram_quantile(0.95, \n    sum(rate(http_server_requests_seconds_bucket{uri=~\"/user.*\"}[1m])) by (le, uri)\n)",
          "hide": false,
          "instant": false,
          "legendFormat": "P95 {{uri}}",
          "range": true,
          "refId": "B"
        },
        {
          "datasource": {
            "type": "prometheus",
            "uid": "prometheus"
          },
          "editorMode": "code",
          "expr": "histogram_quantile(0.99, \n    sum(rate(http_server_requests_seconds_bucket{uri=~\"/user.*\"}[1m])) by (le, uri)\n)",
          "hide": false,
          "instant": false,
          "legendFormat": "P99 {{uri}}",
          "range": true,
          "refId": "C"
        },
        {
          "datasource": {
            "type": "prometheus",
            "uid": "prometheus"
          },
          "editorMode": "code",
          "expr": "histogram_quantile(1, \n    sum(rate(http_server_requests_seconds_bucket{uri=~\"/user.*\"}[1m])) by (le, uri)\n)",
          "hide": false,
          "instant": false,
          "legendFormat": "P100 {{uri}}",
          "range": true,
          "refId": "D"
        }
      ],
      "title": "API Latency",
      "type": "timeseries"
    },
    {
      "collapsed": false,
      "gridPos": {
        "h": 1,
        "w": 24,
        "x": 0,
        "y": 14
      },
      "id": 10,
      "panels": [],
      "title": "Nginx Ingress Resource Metrics",
      "type": "row"
    },
    {
      "datasource": {
        "type": "prometheus",
        "uid": "prometheus"
      },
      "fieldConfig": {
        "defaults": {
          "color": {
            "mode": "palette-classic"
          },
          "custom": {
            "axisCenteredZero": false,
            "axisColorMode": "text",
            "axisLabel": "",
            "axisPlacement": "auto",
            "barAlignment": 0,
            "drawStyle": "line",
            "fillOpacity": 10,
            "gradientMode": "none",
            "hideFrom": {
              "legend": false,
              "tooltip": false,
              "viz": false
            },
            "insertNulls": false,
            "lineInterpolation": "linear",
            "lineWidth": 2,
            "pointSize": 5,
            "scaleDistribution": {
              "type": "linear"
            },
            "showPoints": "never",
            "spanNulls": true,
            "stacking": {
              "group": "A",
              "mode": "none"
            },
            "thresholdsStyle": {
              "mode": "off"
            }
          },
          "mappings": [],
          "thresholds": {
            "mode": "absolute",
            "steps": [
              {
                "color": "green",
                "value": null
              },
              {
                "color": "red",
                "value": 80
              }
            ]
          },
          "unit": "reqps"
        },
        "overrides": [
          {
            "matcher": {
              "id": "byValue",
              "options": {
                "op": "gte",
                "reducer": "allIsZero",
                "value": 0
              }
            },
            "properties": [
              {
                "id": "custom.hideFrom",
                "value": {
                  "legend": true,
                  "tooltip": true,
                  "viz": false
                }
              }
            ]
          }
        ]
      },
      "gridPos": {
        "h": 7,
        "w": 12,
        "x": 0,
        "y": 15
      },
      "id": 18,
      "links": [],
      "options": {
        "legend": {
          "calcs": [
            "mean"
          ],
          "displayMode": "table",
          "placement": "right",
          "showLegend": true,
          "width": 300
        },
        "tooltip": {
          "mode": "multi",
          "sort": "desc"
        }
      },
      "pluginVersion": "10.1.5",
      "repeatDirection": "h",
      "targets": [
        {
          "datasource": {
            "type": "prometheus",
            "uid": "prometheus"
          },
          "editorMode": "code",
          "expr": "round(sum(irate(nginx_ingress_controller_requests[2m])) by (ingress), 0.001)",
          "format": "time_series",
          "hide": false,
          "instant": false,
          "interval": "",
          "intervalFactor": 1,
          "legendFormat": "{{ ingress }}",
          "metric": "network",
          "refId": "A",
          "step": 10
        }
      ],
      "title": "Ingress RPS",
      "type": "timeseries"
    },
    {
      "datasource": {
        "type": "prometheus",
        "uid": "prometheus"
      },
      "fieldConfig": {
        "defaults": {
          "color": {
            "fixedColor": "red",
            "mode": "fixed"
          },
          "mappings": [
            {
              "options": {
                "match": "null+nan",
                "result": {
                  "index": 0,
                  "text": "0%"
                }
              },
              "type": "special"
            }
          ],
          "thresholds": {
            "mode": "percentage",
            "steps": [
              {
                "color": "rgba(245, 54, 54, 0.9)",
                "value": null
              }
            ]
          },
          "unit": "percentunit"
        },
        "overrides": []
      },
      "gridPos": {
        "h": 5,
        "w": 5,
        "x": 12,
        "y": 15
      },
      "id": 21,
      "links": [],
      "maxDataPoints": 100,
      "options": {
        "colorMode": "none",
        "graphMode": "area",
        "justifyMode": "auto",
        "orientation": "horizontal",
        "reduceOptions": {
          "calcs": [],
          "fields": "",
          "values": false
        },
        "textMode": "auto"
      },
      "pluginVersion": "10.1.5",
      "targets": [
        {
          "datasource": {
            "type": "prometheus",
            "uid": "prometheus"
          },
          "editorMode": "code",
          "exemplar": false,
          "expr": "sum(increase(nginx_ingress_controller_request_duration_seconds_count{status=~\"4..|5..\"}[1m])) /sum(increase(nginx_ingress_controller_request_duration_seconds_count[1m]))",
          "format": "table",
          "instant": false,
          "intervalFactor": 1,
          "legendFormat": "__auto",
          "range": true,
          "refId": "A",
          "step": 4
        }
      ],
      "title": "Ingress Error Rate (4|5xx responses)",
      "type": "stat"
    },
    {
      "datasource": {
        "type": "prometheus",
        "uid": "prometheus"
      },
      "fieldConfig": {
        "defaults": {
          "color": {
            "fixedColor": "green",
            "mode": "fixed"
          },
          "mappings": [
            {
              "options": {
                "match": "null+nan",
                "result": {
                  "index": 0,
                  "text": "0%"
                }
              },
              "type": "special"
            }
          ],
          "thresholds": {
            "mode": "percentage",
            "steps": [
              {
                "color": "rgba(245, 54, 54, 0.9)",
                "value": null
              }
            ]
          },
          "unit": "percentunit"
        },
        "overrides": []
      },
      "gridPos": {
        "h": 5,
        "w": 5,
        "x": 17,
        "y": 15
      },
      "id": 23,
      "links": [],
      "maxDataPoints": 100,
      "options": {
        "colorMode": "none",
        "graphMode": "area",
        "justifyMode": "auto",
        "orientation": "horizontal",
        "reduceOptions": {
          "calcs": [],
          "fields": "",
          "values": false
        },
        "textMode": "auto"
      },
      "pluginVersion": "10.1.5",
      "targets": [
        {
          "datasource": {
            "type": "prometheus",
            "uid": "prometheus"
          },
          "editorMode": "code",
          "exemplar": false,
          "expr": "sum(increase(nginx_ingress_controller_request_duration_seconds_count{status!~\"4..|5..\"}[1m])) /sum(increase(nginx_ingress_controller_request_duration_seconds_count[1m]))",
          "format": "table",
          "instant": false,
          "intervalFactor": 1,
          "legendFormat": "__auto",
          "range": true,
          "refId": "A",
          "step": 4
        }
      ],
      "title": "Ingress Success Rate  (non 4|5xx responses)",
      "type": "stat"
    },
    {
      "datasource": {
        "type": "prometheus",
        "uid": "prometheus"
      },
      "fieldConfig": {
        "defaults": {
          "color": {
            "mode": "palette-classic"
          },
          "custom": {
            "axisCenteredZero": false,
            "axisColorMode": "text",
            "axisLabel": "",
            "axisPlacement": "auto",
            "barAlignment": 0,
            "drawStyle": "line",
            "fillOpacity": 0,
            "gradientMode": "none",
            "hideFrom": {
              "legend": false,
              "tooltip": false,
              "viz": false
            },
            "insertNulls": false,
            "lineInterpolation": "smooth",
            "lineWidth": 1,
            "pointSize": 5,
            "scaleDistribution": {
              "type": "linear"
            },
            "showPoints": "auto",
            "spanNulls": false,
            "stacking": {
              "group": "A",
              "mode": "none"
            },
            "thresholdsStyle": {
              "mode": "off"
            }
          },
          "mappings": [],
          "thresholds": {
            "mode": "absolute",
            "steps": [
              {
                "color": "green",
                "value": null
              },
              {
                "color": "red",
                "value": 80
              }
            ]
          },
          "unit": "s"
        },
        "overrides": []
      },
      "gridPos": {
        "h": 7,
        "w": 12,
        "x": 0,
        "y": 22
      },
      "hideTimeOverride": false,
      "id": 11,
      "links": [],
      "options": {
        "legend": {
          "calcs": [],
          "displayMode": "list",
          "placement": "bottom",
          "showLegend": true
        },
        "tooltip": {
          "mode": "multi",
          "sort": "none"
        }
      },
      "pluginVersion": "8.3.4",
      "repeatDirection": "h",
      "targets": [
        {
          "datasource": {
            "type": "prometheus",
            "uid": "P1809F7CD0C75ACF3"
          },
          "editorMode": "code",
          "exemplar": true,
          "expr": "histogram_quantile(0.50, sum(rate(nginx_ingress_controller_request_duration_seconds_bucket[2m])) by (le))",
          "format": "time_series",
          "hide": false,
          "instant": false,
          "interval": "",
          "intervalFactor": 1,
          "legendFormat": "P50",
          "refId": "C"
        },
        {
          "datasource": {
            "type": "prometheus",
            "uid": "P1809F7CD0C75ACF3"
          },
          "editorMode": "code",
          "exemplar": true,
          "expr": "histogram_quantile(0.95, sum(rate(nginx_ingress_controller_request_duration_seconds_bucket[2m])) by (le))",
          "format": "time_series",
          "hide": false,
          "instant": false,
          "interval": "",
          "intervalFactor": 1,
          "legendFormat": "P95",
          "refId": "D"
        },
        {
          "datasource": {
            "type": "prometheus",
            "uid": "P1809F7CD0C75ACF3"
          },
          "editorMode": "code",
          "exemplar": true,
          "expr": "histogram_quantile(0.99, sum(rate(nginx_ingress_controller_request_duration_seconds_bucket[2m])) by (le))",
          "format": "time_series",
          "hide": false,
          "instant": false,
          "interval": "",
          "intervalFactor": 1,
          "legendFormat": "P99",
          "refId": "E"
        },
        {
          "datasource": {
            "type": "prometheus",
            "uid": "prometheus"
          },
          "editorMode": "code",
          "expr": "histogram_quantile(1, sum(rate(nginx_ingress_controller_request_duration_seconds_bucket[2m])) by (le))",
          "hide": false,
          "instant": false,
          "legendFormat": "P100",
          "range": true,
          "refId": "A"
        }
      ],
      "title": "Ingress Latency",
      "type": "timeseries"
    },
    {
      "collapsed": false,
      "gridPos": {
        "h": 1,
        "w": 24,
        "x": 0,
        "y": 29
      },
      "id": 8,
      "panels": [],
      "title": "Pod Resource Metrics",
      "type": "row"
    },
    {
      "datasource": {
        "type": "prometheus",
        "uid": "prometheus"
      },
      "fieldConfig": {
        "defaults": {
          "color": {
            "mode": "palette-classic"
          },
          "custom": {
            "axisCenteredZero": false,
            "axisColorMode": "text",
            "axisLabel": "",
            "axisPlacement": "auto",
            "barAlignment": 0,
            "drawStyle": "line",
            "fillOpacity": 10,
            "gradientMode": "none",
            "hideFrom": {
              "legend": false,
              "tooltip": false,
              "viz": false
            },
            "insertNulls": false,
            "lineInterpolation": "linear",
            "lineWidth": 1,
            "pointSize": 5,
            "scaleDistribution": {
              "type": "linear"
            },
            "showPoints": "never",
            "spanNulls": false,
            "stacking": {
              "group": "A",
              "mode": "none"
            },
            "thresholdsStyle": {
              "mode": "off"
            }
          },
          "mappings": [],
          "thresholds": {
            "mode": "absolute",
            "steps": [
              {
                "color": "green",
                "value": null
              },
              {
                "color": "red",
                "value": 80
              }
            ]
          },
          "unit": "percent"
        },
        "overrides": []
      },
      "gridPos": {
        "h": 9,
        "w": 12,
        "x": 0,
        "y": 30
      },
      "id": 6,
      "links": [],
      "options": {
        "legend": {
          "calcs": [],
          "displayMode": "list",
          "placement": "right",
          "showLegend": true
        },
        "tooltip": {
          "mode": "multi",
          "sort": "none"
        }
      },
      "pluginVersion": "10.1.5",
      "targets": [
        {
          "datasource": {
            "type": "prometheus",
            "uid": "prometheus"
          },
          "editorMode": "code",
          "expr": "avg(irate(container_cpu_usage_seconds_total[5m]) * 100) by (pod)",
          "format": "time_series",
          "hide": false,
          "intervalFactor": 1,
          "legendFormat": "",
          "range": true,
          "refId": "A"
        }
      ],
      "title": "CPU",
      "type": "timeseries"
    },
    {
      "datasource": {
        "type": "prometheus",
        "uid": "prometheus"
      },
      "fieldConfig": {
        "defaults": {
          "color": {
            "mode": "palette-classic"
          },
          "custom": {
            "axisCenteredZero": false,
            "axisColorMode": "text",
            "axisLabel": "",
            "axisPlacement": "auto",
            "barAlignment": 0,
            "drawStyle": "line",
            "fillOpacity": 10,
            "gradientMode": "none",
            "hideFrom": {
              "legend": false,
              "tooltip": false,
              "viz": false
            },
            "insertNulls": false,
            "lineInterpolation": "linear",
            "lineWidth": 1,
            "pointSize": 5,
            "scaleDistribution": {
              "type": "linear"
            },
            "showPoints": "never",
            "spanNulls": false,
            "stacking": {
              "group": "A",
              "mode": "none"
            },
            "thresholdsStyle": {
              "mode": "off"
            }
          },
          "mappings": [],
          "thresholds": {
            "mode": "absolute",
            "steps": [
              {
                "color": "green",
                "value": null
              },
              {
                "color": "red",
                "value": 80
              }
            ]
          },
          "unit": "bytes"
        },
        "overrides": []
      },
      "gridPos": {
        "h": 9,
        "w": 12,
        "x": 12,
        "y": 30
      },
      "id": 7,
      "links": [],
      "options": {
        "legend": {
          "calcs": [],
          "displayMode": "list",
          "placement": "right",
          "showLegend": true
        },
        "tooltip": {
          "mode": "multi",
          "sort": "none"
        }
      },
      "pluginVersion": "10.1.5",
      "targets": [
        {
          "datasource": {
            "type": "prometheus",
            "uid": "prometheus"
          },
          "editorMode": "code",
          "expr": "sum (container_memory_working_set_bytes) by (pod)",
          "format": "time_series",
          "intervalFactor": 1,
          "range": true,
          "refId": "A"
        }
      ],
      "title": "Memory",
      "type": "timeseries"
    }
  ],
  "refresh": "30s",
  "schemaVersion": 38,
  "style": "dark",
  "tags": [],
  "templating": {
    "list": []
  },
  "time": {
    "from": "now-5m",
    "to": "now"
  },
  "timepicker": {},
  "timezone": "",
  "title": "APP",
  "uid": "c08271f3-d9e8-4064-b3c5-135c9951df49",
  "version": 50,
  "weekStart": ""
}